kafka_republisher/__init__.py
kafka_republisher/cli.py
kafka_republisher/config.py
kafka_republisher/kafka_client.py
kafka_republisher/processor.py
kafka_republisher/publisher.py
kafka_republisher/republisher.py
kafka_republisher-0.3.0.dist-info/METADATA
kafka_republisher-0.3.0.dist-info/WHEEL
kafka_republisher-0.3.0.dist-info/entry_points.txt
kafka_republisher-0.3.0.dist-info/licenses/LICENSE
kafka_republisher-0.3.0.dist-info/RECORD
