Metadata-Version: 2.4
Name: kafka_republisher
Version: 0.3.0
Summary: Republish kafka message from one topic to another
License: MIT
License-File: LICENSE
Keywords: kafka
Author: Siak Hooi
Author-email: siakhooi@gmail.com
Requires-Python: >=3.10
Classifier: Development Status :: 4 - Beta
Classifier: Environment :: Console
Classifier: License :: OSI Approved :: MIT License
Classifier: Topic :: Utilities
Requires-Dist: confluent-kafka (>=2.12.2,<3.0.0)
Project-URL: Bug Tracker, https://github.com/siakhooi/kafka-republisher/issues
Project-URL: Documentation, https://github.com/siakhooi/kafka-republisher/wiki
Project-URL: Homepage, https://github.com/siakhooi/kafka-republisher
Project-URL: Repository, https://github.com/siakhooi/kafka-republisher
